spaceforge/README.md
spaceforge/__init__.py
spaceforge/__main__.py
spaceforge/_version.py
spaceforge/_version_scm.py
spaceforge/cls.py
spaceforge/conftest.py
spaceforge/generator.py
spaceforge/plugin.py
spaceforge/runner.py
spaceforge/schema.json
spaceforge/test_cls.py
spaceforge/test_generator.py
spaceforge/test_generator_binaries.py
spaceforge/test_generator_core.py
spaceforge/test_generator_hooks.py
spaceforge/test_generator_parameters.py
spaceforge/test_plugin.py
spaceforge/test_plugin_file_operations.py
spaceforge/test_plugin_hooks.py
spaceforge/test_plugin_inheritance.py
spaceforge/test_runner.py
spaceforge/test_runner_cli.py
spaceforge/test_runner_core.py
spaceforge/test_runner_execution.py
spaceforge/templates/binary_install.sh.j2
spaceforge/templates/ensure_spaceforge_and_run.sh.j2
spaceforge-1.2.1.dist-info/licenses/LICENSE
spaceforge-1.2.1.dist-info/METADATA
spaceforge-1.2.1.dist-info/WHEEL
spaceforge-1.2.1.dist-info/entry_points.txt
spaceforge-1.2.1.dist-info/top_level.txt
spaceforge-1.2.1.dist-info/RECORD
